odoo8_addon_stock_available_lot_locked-8.0.1.0.0-py2.7-nspkg.pth
odoo8_addon_stock_available_lot_locked-8.0.1.0.0.dist-info/DESCRIPTION.rst
odoo8_addon_stock_available_lot_locked-8.0.1.0.0.dist-info/METADATA
odoo8_addon_stock_available_lot_locked-8.0.1.0.0.dist-info/RECORD
odoo8_addon_stock_available_lot_locked-8.0.1.0.0.dist-info/WHEEL
odoo8_addon_stock_available_lot_locked-8.0.1.0.0.dist-info/metadata.json
odoo8_addon_stock_available_lot_locked-8.0.1.0.0.dist-info/namespace_packages.txt
odoo8_addon_stock_available_lot_locked-8.0.1.0.0.dist-info/top_level.txt
odoo_addons/stock_available_lot_locked/README.rst
odoo_addons/stock_available_lot_locked/__init__.py
odoo_addons/stock_available_lot_locked/__openerp__.py
odoo_addons/stock_available_lot_locked/i18n/fr.po
odoo_addons/stock_available_lot_locked/models/__init__.py
odoo_addons/stock_available_lot_locked/models/product_product.py
odoo_addons/stock_available_lot_locked/models/product_template.py
odoo_addons/stock_available_lot_locked/tests/__init__.py
odoo_addons/stock_available_lot_locked/tests/test_locked_qty.py
odoo_addons/stock_available_lot_locked/views/product_template_view.xml
